{"version": 0, "name": "All Election Dates in United States by electioncal.us", "description": null, "dates": [{"date": "2020-02-29", "name": "Presidential Primary (Democrats)", "original_date": "2020-02-29", "results": "https://www.enr-scvotes.org/SC/100517/Web02-state.242137/#/", "state": "South Carolina", "county": null, "key": "20200229", "type": "election"}, {"date": "2020-03-03", "name": "Congressional & Presidential Primary", "original_date": "2020-03-03", "state": "Arkansas", "county": null, "key": "20200303", "type": "election"}, {"date": "2020-03-03", "name": "Congressional & Presidential Primary", "original_date": "2020-03-03", "state": "California", "county": null, "key": "20200303", "type": "election"}, {"date": "2020-03-03", "name": "Presidential Primary", "original_date": "2020-03-03", "state": "Colorado", "county": null, "key": "20200303", "type": "election"}, {"date": "2020-03-03", "name": "Presidential Primary", "original_date": "2020-03-03", "state": "Massachusetts", "county": null, "key": "20200303", "type": "election"}, {"date": "2020-03-03", "name": "Presidential Primary", "original_date": "2020-03-03", "state": "Minnesota", "county": null, "key": "20200303", "type": "election"}, {"date": "2020-03-03", "name": "Congressional & Presidential Primary", "original_date": "2020-03-03", "state": "North Carolina", "county": null, "key": "20200303", "type": "election"}, {"date": "2020-03-03", "name": "Presidential Primary", "original_date": "2020-03-03", "state": "Oklahoma", "county": null, "key": "20200303", "type": "election"}, {"date": "2020-03-03", "name": "Presidential Primary", "original_date": "2020-03-03", "state": "Tennessee", "county": null, "key": "20200303", "type": "election"}, {"date": "2020-03-03", "name": "Congressional & Presidential Primary", "original_date": "2020-03-03", "state": "Texas", "county": null, "key": "20200303", "type": "election"}, {"date": "2020-03-03", "name": "Presidential Primary", "original_date": "2020-03-03", "state": "Utah", "county": null, "key": "20200303", "type": "election"}, {"date": "2020-03-03", "name": "Presidential Primary", "original_date": "2020-03-03", "state": "Vermont", "county": null, "key": "20200303", "type": "election"}, {"date": "2020-03-03", "name": "Presidential Primary (Democrats)", "original_date": "2020-03-03", "state": "Virginia", "county": null, "key": "20200303", "type": "election"}, {"date": "2020-03-10", "name": "Presidential Primary", "original_date": "2020-03-10", "state": "Michigan", "county": null, "key": "20200310", "type": "election"}, {"date": "2020-03-10", "name": "Presidential Primary", "original_date": "2020-03-10", "state": "Washington", "county": null, "key": "20200310", "type": "election"}, {"date": "2020-03-17", "name": "Presidential Preference (Democrats)", "original_date": "2020-03-17", "state": "Arizona", "county": null, "key": "20200317", "type": "election"}, {"date": "2020-03-17", "name": "Presidential Primary", "original_date": "2020-03-17", "state": "Florida", "county": null, "key": "20200317", "type": "election"}, {"date": "2020-03-17", "name": "Congressional & Presidential Primary", "original_date": "2020-03-17", "state": "Illinois", "county": null, "key": "20200317", "type": "election"}, {"date": "2020-03-31", "name": "Congressional Primary Run-Off (if needed)", "original_date": "2020-03-31", "state": "Arkansas", "county": null, "key": "20200331", "type": "election"}, {"date": "2020-04-07", "name": "Presidential Primary", "original_date": "2020-04-07", "state": "Wisconsin", "county": null, "key": "20200407", "type": "election"}, {"date": "2020-04-28", "name": "Presidential Primary", "original_date": "2020-04-28", "state": "New York", "county": null, "key": "20200428", "type": "election"}, {"date": "2020-04-28", "name": "Congressional & Presidential Primary", "original_date": "2020-04-28", "state": "Ohio", "county": null, "key": "20200428", "type": "election"}, {"date": "2020-05-12", "name": "Congressional & Presidential Primary", "original_date": "2020-05-12", "state": "Nebraska", "county": null, "key": "20200512", "type": "election"}, {"date": "2020-05-19", "name": "Congressional & Presidential Primary", "original_date": "2020-05-19", "state": "Oregon", "county": null, "key": "20200519", "type": "election"}, {"state": "Mississippi", "county": null, "name": "Mail voter registration", "type": "reminder", "election_key": "20200623", "subtype": "registration.postmarked_by", "date": "2020-05-25", "postmark_too_late": false, "deadline_date": "2020-05-26", "explanation": "Voter registration must be postmarked by May 26th."}, {"state": "Mississippi", "county": null, "name": "Last day to register to vote in person", "type": "deadline", "election_key": "20200623", "subtype": "registration.in_person_by", "date": "2020-05-26"}, {"state": "Mississippi", "county": null, "name": "Last day to postmark voter registration form", "type": "deadline", "election_key": "20200623", "subtype": "registration.postmarked_by", "date": "2020-05-26", "postmark_too_late": false}, {"state": "Mississippi", "county": null, "name": "Register to vote in person", "type": "reminder", "election_key": "20200623", "subtype": "registration.in_person_by", "date": "2020-05-26", "deadline_date": "2020-05-26"}, {"state": "Mississippi", "county": null, "name": "Mail voter registration at the post office", "type": "reminder", "election_key": "20200623", "subtype": "registration.postmarked_by", "date": "2020-05-26", "postmark_too_late": false, "deadline_date": "2020-05-26", "explanation": "Voter registration must be postmarked by May 26th."}, {"state": "New York", "county": null, "name": "Mail voter registration", "type": "reminder", "election_key": "20200623", "subtype": "registration.received_by", "date": "2020-05-26", "postmark_too_late": true, "deadline_date": "2020-06-03", "explanation": "Voter registration must be received by June 3rd."}, {"state": "New York", "county": null, "name": "Mail voter registration at the post office", "type": "reminder", "election_key": "20200623", "subtype": "registration.received_by", "date": "2020-05-27", "postmark_too_late": true, "deadline_date": "2020-06-03", "explanation": "Voter registration must be received by June 3rd."}, {"state": "New York", "county": null, "name": "Last day to postmark voter registration form", "type": "deadline", "election_key": "20200623", "subtype": "registration.postmarked_by", "date": "2020-05-29", "postmark_too_late": true}, {"date": "2020-06-02", "name": "Congressional & Presidential Primary", "original_date": "2020-06-02", "results": "https://electionresults.dcboe.org/election_results/2020-Primary-Election", "state": "District of Columbia", "county": null, "key": "20200602", "type": "election"}, {"date": "2020-06-02", "name": "Congressional Primary", "original_date": "2020-05-19", "results": "https://www.livevoterturnout.com/Idaho/LiveResults/1/en/Index_112.html", "state": "Idaho", "county": null, "key": "20200519", "type": "election"}, {"date": "2020-06-02", "name": "Congressional & Presidential Primary", "original_date": "2020-06-02", "results": "https://enr.indianavoters.in.gov/site/index.html", "state": "Indiana", "county": null, "key": "20200602", "type": "election"}, {"date": "2020-06-02", "name": "Congressional Primary", "original_date": "2020-06-02", "state": "Iowa", "county": null, "key": "20200602", "type": "election"}, {"date": "2020-06-02", "name": "Congressional & Presidential Primary", "original_date": "2020-06-02", "state": "Maryland", "county": null, "key": "20200602", "type": "election"}, {"date": "2020-06-02", "name": "Congressional & Presidential Primary", "original_date": "2020-06-02", "state": "Montana", "county": null, "key": "20200602", "type": "election"}, {"date": "2020-06-02", "name": "Congressional & Presidential Primary", "original_date": "2020-06-02", "state": "New Mexico", "county": null, "key": "20200602", "type": "election"}, {"date": "2020-06-02", "name": "Congressional & Presidential Primary", "original_date": "2020-06-02", "state": "Pennsylvania", "county": null, "key": "20200602", "type": "election"}, {"date": "2020-06-02", "name": "Presidential Primary", "original_date": "2020-06-02", "state": "Rhode Island", "county": null, "key": "20200602", "type": "election"}, {"date": "2020-06-02", "name": "Congressional & Presidential Primary", "original_date": "2020-06-02", "state": "South Dakota", "county": null, "key": "20200602", "type": "election"}, {"state": "New York", "county": null, "name": "Last day for election officials to receive voter registration form", "type": "deadline", "election_key": "20200623", "subtype": "registration.received_by", "date": "2020-06-03", "postmark_too_late": true}, {"state": "Delaware", "county": null, "name": "Mail voter registration", "type": "reminder", "election_key": "20200707", "subtype": "registration.received_by", "date": "2020-06-05", "postmark_too_late": true, "deadline_date": "2020-06-13", "explanation": "Voter registration must be received by June 13th."}, {"state": "Delaware", "county": null, "name": "Mail voter registration at the post office", "type": "reminder", "election_key": "20200707", "subtype": "registration.received_by", "date": "2020-06-06", "postmark_too_late": true, "deadline_date": "2020-06-13", "explanation": "Voter registration must be received by June 13th."}, {"date": "2020-06-07", "name": "Presidential Primary (Republican)", "original_date": "2020-06-07", "state": "Puerto Rico", "county": null, "key": "20200607", "type": "election"}, {"state": "North Carolina", "county": null, "name": "Mail absentee application", "type": "reminder", "election_key": "20200512", "subtype": "absentee.application.received_by", "date": "2020-06-08", "postmark_too_late": true, "deadline_date": "2020-06-16", "explanation": "Absentee application must be received by June 16th."}, {"date": "2020-06-09", "name": "Presidential Primary", "original_date": "2020-06-09", "state": "Georgia", "county": null, "key": "20200609", "type": "election"}, {"date": "2020-06-09", "name": "Congressional Primary", "original_date": "2020-06-09", "state": "Nevada", "county": null, "key": "20200609", "type": "election"}, {"date": "2020-06-09", "name": "Congressional Primary", "original_date": "2020-06-09", "state": "North Dakota", "county": null, "key": "20200609", "type": "election"}, {"date": "2020-06-09", "name": "Congressional Primary", "original_date": "2020-06-09", "results": "https://www.enr-scvotes.org/SC/103402/Web02-state.250556/#/", "state": "South Carolina", "county": null, "key": "20200609", "type": "election"}, {"date": "2020-06-09", "name": "Congressional & Presidential Primary", "original_date": "2020-06-09", "state": "West Virginia", "county": null, "key": "20200609", "type": "election"}, {"state": "North Carolina", "county": null, "name": "Mail absentee application at the post office", "type": "reminder", "election_key": "20200512", "subtype": "absentee.application.received_by", "date": "2020-06-09", "postmark_too_late": true, "deadline_date": "2020-06-16", "explanation": "Absentee application must be received by June 16th."}, {"state": "Utah", "county": null, "name": "Mail voter registration", "type": "reminder", "election_key": "20200630", "subtype": "registration.received_by", "date": "2020-06-11", "postmark_too_late": true, "deadline_date": "2020-06-19", "explanation": "Voter registration must be received by June 19th."}, {"state": "Utah", "county": null, "name": "Mail voter registration at the post office", "type": "reminder", "election_key": "20200630", "subtype": "registration.received_by", "date": "2020-06-12", "postmark_too_late": true, "deadline_date": "2020-06-19", "explanation": "Voter registration must be received by June 19th."}, {"state": "Delaware", "county": null, "name": "Last day for election officials to receive voter registration form", "type": "deadline", "election_key": "20200707", "subtype": "registration.received_by", "date": "2020-06-13", "postmark_too_late": true}, {"state": "New York", "county": null, "name": "Last day to register to vote in person", "type": "deadline", "election_key": "20200623", "subtype": "registration.in_person_by", "date": "2020-06-13"}, {"state": "New York", "county": null, "name": "Register to vote in person", "type": "reminder", "election_key": "20200623", "subtype": "registration.in_person_by", "date": "2020-06-13", "deadline_date": "2020-06-13"}, {"state": "Colorado", "county": null, "name": "Mail voter registration", "type": "reminder", "election_key": "20200630", "subtype": "registration.received_by", "date": "2020-06-14", "postmark_too_late": true, "deadline_date": "2020-06-22", "explanation": "Voter registration must be received by June 22nd."}, {"state": "Mississippi", "county": null, "name": "Mail ballot", "type": "reminder", "election_key": "20200623", "subtype": "absentee.received_by", "date": "2020-06-14", "postmark_too_late": true, "deadline_date": "2020-06-22", "explanation": "Ballot must be received by June 22nd."}, {"state": "Colorado", "county": null, "name": "Mail voter registration at the post office", "type": "reminder", "election_key": "20200630", "subtype": "registration.received_by", "date": "2020-06-15", "postmark_too_late": true, "deadline_date": "2020-06-22", "explanation": "Voter registration must be received by June 22nd."}, {"state": "Kentucky", "county": null, "name": "Last day to apply online for a mail-in ballot", "type": "deadline", "election_key": "20200623", "subtype": "absentee.application.online_by", "date": "2020-06-15"}, {"state": "Kentucky", "county": null, "name": "Apply for an absentee ballot online", "type": "reminder", "election_key": "20200623", "subtype": "absentee.application.online_by", "date": "2020-06-15", "deadline_date": "2020-06-15"}, {"state": "Mississippi", "county": null, "name": "Mail ballot at the post office", "type": "reminder", "election_key": "20200623", "subtype": "absentee.received_by", "date": "2020-06-15", "postmark_too_late": true, "deadline_date": "2020-06-22", "explanation": "Ballot must be received by June 22nd."}, {"state": "New York", "county": null, "name": "Mail absentee application", "type": "reminder", "election_key": "20200623", "subtype": "absentee.application.postmarked_by", "date": "2020-06-15", "postmark_too_late": false, "deadline_date": "2020-06-16", "explanation": "Absentee application must be postmarked by June 16th."}, {"state": "South Carolina", "county": null, "name": "Mail ballot", "type": "reminder", "election_key": "20200623", "subtype": "absentee.received_by", "date": "2020-06-15", "postmark_too_late": true, "deadline_date": "2020-06-23", "explanation": "Ballot must be received by June 23rd."}, {"state": "Virginia", "county": null, "name": "Mail ballot", "type": "reminder", "election_key": "20200623", "subtype": "absentee.received_by", "date": "2020-06-15", "postmark_too_late": true, "deadline_date": "2020-06-23", "explanation": "Ballot must be received by June 23rd."}, {"state": "New York", "county": null, "name": "Last day to postmark absentee applications", "type": "deadline", "election_key": "20200623", "subtype": "absentee.application.postmarked_by", "date": "2020-06-16", "postmark_too_late": false}, {"state": "New York", "county": null, "name": "Mail absentee application at the post office", "type": "reminder", "election_key": "20200623", "subtype": "absentee.application.postmarked_by", "date": "2020-06-16", "postmark_too_late": false, "deadline_date": "2020-06-16", "explanation": "Absentee application must be postmarked by June 16th."}, {"state": "North Carolina", "county": null, "name": "Last day for election officials to receive absentee applications", "type": "deadline", "election_key": "20200512", "subtype": "absentee.application.received_by", "date": "2020-06-16", "postmark_too_late": true}, {"state": "North Carolina", "county": null, "name": "Last day to hand deliver an absentee applications", "type": "deadline", "election_key": "20200512", "subtype": "absentee.application.in_person_by", "date": "2020-06-16"}, {"state": "North Carolina", "county": null, "name": "Drop off absentee application", "type": "reminder", "election_key": "20200512", "subtype": "absentee.application.in_person_by", "date": "2020-06-16", "deadline_date": "2020-06-16"}, {"state": "South Carolina", "county": null, "name": "Mail ballot at the post office", "type": "reminder", "election_key": "20200623", "subtype": "absentee.received_by", "date": "2020-06-16", "postmark_too_late": true, "deadline_date": "2020-06-23", "explanation": "Ballot must be received by June 23rd."}, {"state": "Virginia", "county": null, "name": "Mail ballot at the post office", "type": "reminder", "election_key": "20200623", "subtype": "absentee.received_by", "date": "2020-06-16", "postmark_too_late": true, "deadline_date": "2020-06-23", "explanation": "Ballot must be received by June 23rd."}, {"state": "North Carolina", "county": null, "name": "Mail ballot", "type": "reminder", "election_key": "20200512", "subtype": "absentee.received_by", "date": "2020-06-18", "postmark_too_late": true, "deadline_date": "2020-06-26", "explanation": "Ballot must be received by June 26th."}, {"state": "Kentucky", "county": null, "name": "Mail ballot", "type": "reminder", "election_key": "20200623", "subtype": "absentee.received_by", "date": "2020-06-19", "postmark_too_late": true, "deadline_date": "2020-06-27", "explanation": "Ballot must be received by June 27th."}, {"state": "North Carolina", "county": null, "name": "Mail ballot at the post office", "type": "reminder", "election_key": "20200512", "subtype": "absentee.received_by", "date": "2020-06-19", "postmark_too_late": true, "deadline_date": "2020-06-26", "explanation": "Ballot must be received by June 26th."}, {"state": "Utah", "county": null, "name": "Last day for election officials to receive voter registration form", "type": "deadline", "election_key": "20200630", "subtype": "registration.received_by", "date": "2020-06-19", "postmark_too_late": true}, {"state": "Kentucky", "county": null, "name": "Mail ballot at the post office", "type": "reminder", "election_key": "20200623", "subtype": "absentee.received_by", "date": "2020-06-20", "postmark_too_late": true, "deadline_date": "2020-06-27", "explanation": "Ballot must be received by June 27th."}, {"state": "New York", "county": null, "name": "Last day to vote early in person", "type": "deadline", "election_key": "20200623", "subtype": "poll.early.in_person_by", "date": "2020-06-21"}, {"state": "New York", "county": null, "name": "Vote early in person", "type": "reminder", "election_key": "20200623", "subtype": "poll.early.in_person_by", "date": "2020-06-21", "deadline_date": "2020-06-21"}, {"state": "New York", "county": null, "name": "Mail ballot", "type": "reminder", "election_key": "20200623", "subtype": "absentee.postmarked_by", "date": "2020-06-21", "postmark_too_late": false, "deadline_date": "2020-06-22", "explanation": "Ballot must be postmarked by June 22nd."}, {"state": "Colorado", "county": null, "name": "Last day for election officials to receive voter registration form", "type": "deadline", "election_key": "20200630", "subtype": "registration.received_by", "date": "2020-06-22", "postmark_too_late": true}, {"state": "Kentucky", "county": null, "name": "Plan to vote", "type": "reminder", "election_key": "20200623", "subtype": "poll.in_person_by", "date": "2020-06-22", "deadline_date": "2020-06-23"}, {"state": "Mississippi", "county": null, "name": "Last day for election officials to receive absentee ballots", "type": "deadline", "election_key": "20200623", "subtype": "absentee.received_by", "date": "2020-06-22", "postmark_too_late": true}, {"state": "Mississippi", "county": null, "name": "Plan to vote", "type": "reminder", "election_key": "20200623", "subtype": "poll.in_person_by", "date": "2020-06-22", "deadline_date": "2020-06-23"}, {"state": "New York", "county": null, "name": "Last day to postmark absentee ballots", "type": "deadline", "election_key": "20200623", "subtype": "absentee.postmarked_by", "date": "2020-06-22", "postmark_too_late": false}, {"state": "New York", "county": null, "name": "Last day to hand deliver an absentee applications", "type": "deadline", "election_key": "20200623", "subtype": "absentee.application.in_person_by", "date": "2020-06-22"}, {"state": "New York", "county": null, "name": "Mail ballot at the post office", "type": "reminder", "election_key": "20200623", "subtype": "absentee.postmarked_by", "date": "2020-06-22", "postmark_too_late": false, "deadline_date": "2020-06-22", "explanation": "Ballot must be postmarked by June 22nd."}, {"state": "New York", "county": null, "name": "Drop off absentee application", "type": "reminder", "election_key": "20200623", "subtype": "absentee.application.in_person_by", "date": "2020-06-22", "deadline_date": "2020-06-22"}, {"state": "New York", "county": null, "name": "Plan to vote", "type": "reminder", "election_key": "20200623", "subtype": "poll.in_person_by", "date": "2020-06-22", "deadline_date": "2020-06-23"}, {"state": "North Carolina", "county": null, "name": "Plan to vote", "type": "reminder", "election_key": "20200512", "subtype": "poll.in_person_by", "date": "2020-06-22", "deadline_date": "2020-06-23"}, {"state": "Oklahoma", "county": null, "name": "Mail ballot", "type": "reminder", "election_key": "20200630", "subtype": "absentee.received_by", "date": "2020-06-22", "postmark_too_late": true, "deadline_date": "2020-06-30", "explanation": "Ballot must be received by June 30th."}, {"state": "South Carolina", "county": null, "name": "Plan to vote", "type": "reminder", "election_key": "20200623", "subtype": "poll.in_person_by", "date": "2020-06-22", "deadline_date": "2020-06-23"}, {"state": "Virginia", "county": null, "name": "Plan to vote", "type": "reminder", "election_key": "20200623", "subtype": "poll.in_person_by", "date": "2020-06-22", "deadline_date": "2020-06-23"}, {"date": "2020-06-23", "name": "Presidential Primary", "original_date": "2020-06-23", "absentee": {}, "poll": {}, "state": "Kentucky", "county": null, "key": "20200623", "type": "election"}, {"date": "2020-06-23", "name": "Congressional Primary Run-Off", "original_date": "2020-06-23", "registration": {}, "absentee": {}, "poll": {}, "state": "Mississippi", "county": null, "key": "20200623", "type": "election"}, {"date": "2020-06-23", "name": "Congressional Primary", "original_date": "2020-06-23", "registration": {}, "poll": {}, "absentee": {}, "state": "New York", "county": null, "key": "20200623", "type": "election"}, {"date": "2020-06-23", "name": "Congressional Primary Run-Off", "original_date": "2020-05-12", "absentee": {}, "poll": {}, "state": "North Carolina", "county": null, "key": "20200512", "type": "election"}, {"date": "2020-06-23", "name": "Congressional Primary\u00a0Run-Off", "original_date": "2020-06-23", "poll": {}, "absentee": {}, "state": "South Carolina", "county": null, "key": "20200623", "type": "election"}, {"date": "2020-06-23", "name": "Congressional Primary", "original_date": "2020-06-23", "poll": {}, "absentee": {}, "state": "Virginia", "county": null, "key": "20200623", "type": "election"}, {"state": "Kentucky", "county": null, "name": "Last day to postmark absentee ballots", "type": "deadline", "election_key": "20200623", "subtype": "absentee.postmarked_by", "date": "2020-06-23", "postmark_too_late": true}, {"state": "Kentucky", "county": null, "name": "Last day to vote in person", "type": "deadline", "election_key": "20200623", "subtype": "poll.in_person_by", "date": "2020-06-23"}, {"state": "Kentucky", "county": null, "name": "Vote in person", "type": "reminder", "election_key": "20200623", "subtype": "poll.in_person_by", "date": "2020-06-23", "deadline_date": "2020-06-23", "start_date": "2020-06-23"}, {"state": "Mississippi", "county": null, "name": "Last day to vote in person", "type": "deadline", "election_key": "20200623", "subtype": "poll.in_person_by", "date": "2020-06-23"}, {"state": "Mississippi", "county": null, "name": "Vote in person", "type": "reminder", "election_key": "20200623", "subtype": "poll.in_person_by", "date": "2020-06-23", "deadline_date": "2020-06-23", "start_date": "2020-06-23"}, {"state": "New York", "county": null, "name": "Last day to drop off an absentee ballot", "type": "deadline", "election_key": "20200623", "subtype": "absentee.in_person_by", "date": "2020-06-23"}, {"state": "New York", "county": null, "name": "Last day to vote in person", "type": "deadline", "election_key": "20200623", "subtype": "poll.in_person_by", "date": "2020-06-23"}, {"state": "New York", "county": null, "name": "Drop off ballot", "type": "reminder", "election_key": "20200623", "subtype": "absentee.in_person_by", "date": "2020-06-23", "deadline_date": "2020-06-23"}, {"state": "New York", "county": null, "name": "Vote in person", "type": "reminder", "election_key": "20200623", "subtype": "poll.in_person_by", "date": "2020-06-23", "deadline_date": "2020-06-23", "start_date": "2020-06-23"}, {"state": "North Carolina", "county": null, "name": "Last day to drop off an absentee ballot", "type": "deadline", "election_key": "20200512", "subtype": "absentee.in_person_by", "date": "2020-06-23"}, {"state": "North Carolina", "county": null, "name": "Last day to postmark absentee ballots", "type": "deadline", "election_key": "20200512", "subtype": "absentee.postmarked_by", "date": "2020-06-23", "postmark_too_late": true}, {"state": "North Carolina", "county": null, "name": "Last day to vote in person", "type": "deadline", "election_key": "20200512", "subtype": "poll.in_person_by", "date": "2020-06-23"}, {"state": "North Carolina", "county": null, "name": "Drop off ballot", "type": "reminder", "election_key": "20200512", "subtype": "absentee.in_person_by", "date": "2020-06-23", "deadline_date": "2020-06-23"}, {"state": "North Carolina", "county": null, "name": "Vote in person", "type": "reminder", "election_key": "20200512", "subtype": "poll.in_person_by", "date": "2020-06-23", "deadline_date": "2020-06-23", "start_date": "2020-06-23"}, {"state": "Oklahoma", "county": null, "name": "Mail ballot at the post office", "type": "reminder", "election_key": "20200630", "subtype": "absentee.received_by", "date": "2020-06-23", "postmark_too_late": true, "deadline_date": "2020-06-30", "explanation": "Ballot must be received by June 30th."}, {"state": "South Carolina", "county": null, "name": "Last day for election officials to receive absentee ballots", "type": "deadline", "election_key": "20200623", "subtype": "absentee.received_by", "date": "2020-06-23", "postmark_too_late": true}, {"state": "South Carolina", "county": null, "name": "Last day to drop off an absentee ballot", "type": "deadline", "election_key": "20200623", "subtype": "absentee.in_person_by", "date": "2020-06-23"}, {"state": "South Carolina", "county": null, "name": "Last day to vote in person", "type": "deadline", "election_key": "20200623", "subtype": "poll.in_person_by", "date": "2020-06-23"}, {"state": "South Carolina", "county": null, "name": "Drop off ballot", "type": "reminder", "election_key": "20200623", "subtype": "absentee.in_person_by", "date": "2020-06-23", "deadline_date": "2020-06-23"}, {"state": "South Carolina", "county": null, "name": "Vote in person", "type": "reminder", "election_key": "20200623", "subtype": "poll.in_person_by", "date": "2020-06-23", "deadline_date": "2020-06-23", "start_date": "2020-06-23"}, {"state": "Virginia", "county": null, "name": "Last day for election officials to receive absentee ballots", "type": "deadline", "election_key": "20200623", "subtype": "absentee.received_by", "date": "2020-06-23", "postmark_too_late": true}, {"state": "Virginia", "county": null, "name": "Last day to drop off an absentee ballot", "type": "deadline", "election_key": "20200623", "subtype": "absentee.in_person_by", "date": "2020-06-23"}, {"state": "Virginia", "county": null, "name": "Last day to vote in person", "type": "deadline", "election_key": "20200623", "subtype": "poll.in_person_by", "date": "2020-06-23"}, {"state": "Virginia", "county": null, "name": "Drop off ballot", "type": "reminder", "election_key": "20200623", "subtype": "absentee.in_person_by", "date": "2020-06-23", "deadline_date": "2020-06-23"}, {"state": "Virginia", "county": null, "name": "Vote in person", "type": "reminder", "election_key": "20200623", "subtype": "poll.in_person_by", "date": "2020-06-23", "deadline_date": "2020-06-23", "start_date": "2020-06-23"}, {"state": "North Carolina", "county": null, "name": "Last day for election officials to receive absentee ballots", "type": "deadline", "election_key": "20200512", "subtype": "absentee.received_by", "date": "2020-06-26", "postmark_too_late": true}, {"state": "Kentucky", "county": null, "name": "Last day for election officials to receive absentee ballots", "type": "deadline", "election_key": "20200623", "subtype": "absentee.received_by", "date": "2020-06-27", "postmark_too_late": true}, {"state": "Oklahoma", "county": null, "name": "Last day to drop off an absentee ballot", "type": "deadline", "election_key": "20200630", "subtype": "absentee.in_person_by", "date": "2020-06-27"}, {"state": "Oklahoma", "county": null, "name": "Drop off ballot", "type": "reminder", "election_key": "20200630", "subtype": "absentee.in_person_by", "date": "2020-06-27", "deadline_date": "2020-06-27"}, {"state": "Colorado", "county": null, "name": "Plan to vote", "type": "reminder", "election_key": "20200630", "subtype": "poll.in_person_by", "date": "2020-06-29", "deadline_date": "2020-06-30"}, {"state": "Delaware", "county": null, "name": "Mail ballot", "type": "reminder", "election_key": "20200707", "subtype": "absentee.received_by", "date": "2020-06-29", "postmark_too_late": true, "deadline_date": "2020-07-07", "explanation": "Ballot must be received by July 7th."}, {"state": "Oklahoma", "county": null, "name": "Plan to vote", "type": "reminder", "election_key": "20200630", "subtype": "poll.in_person_by", "date": "2020-06-29", "deadline_date": "2020-06-30"}, {"date": "2020-06-30", "name": "Congressional Primary", "original_date": "2020-06-30", "absentee": {}, "registration": {}, "poll": {}, "state": "Colorado", "county": null, "key": "20200630", "type": "election"}, {"date": "2020-06-30", "name": "Congressional Primary", "original_date": "2020-06-30", "sources": ["https://www.ok.gov/elections/Election_Info/2020_Election_Calendar.html"], "register": {}, "absentee": {}, "poll": {}, "state": "Oklahoma", "county": null, "key": "20200630", "type": "election"}, {"date": "2020-06-30", "name": "Congressional Primary", "original_date": "2020-06-30", "registration": {}, "absentee": {}, "state": "Utah", "county": null, "key": "20200630", "type": "election"}, {"state": "Colorado", "county": null, "name": "Last day to vote in person", "type": "deadline", "election_key": "20200630", "subtype": "poll.in_person_by", "date": "2020-06-30"}, {"state": "Colorado", "county": null, "name": "Last day to register to vote in person", "type": "deadline", "election_key": "20200630", "subtype": "registration.in_person_by", "date": "2020-06-30"}, {"state": "Colorado", "county": null, "name": "Vote in person", "type": "reminder", "election_key": "20200630", "subtype": "poll.in_person_by", "date": "2020-06-30", "deadline_date": "2020-06-30", "start_date": "2020-06-30"}, {"state": "Colorado", "county": null, "name": "Register to vote in person", "type": "reminder", "election_key": "20200630", "subtype": "registration.in_person_by", "date": "2020-06-30", "deadline_date": "2020-06-30"}, {"state": "Colorado", "county": null, "name": "Mail ballot", "type": "reminder", "election_key": "20200630", "subtype": "absentee.overseas_military.received_by", "date": "2020-06-30", "postmark_too_late": true, "deadline_date": "2020-07-08", "explanation": "Ballot must be received by July 8th."}, {"state": "Delaware", "county": null, "name": "Mail ballot at the post office", "type": "reminder", "election_key": "20200707", "subtype": "absentee.received_by", "date": "2020-06-30", "postmark_too_late": true, "deadline_date": "2020-07-07", "explanation": "Ballot must be received by July 7th."}, {"state": "New York", "county": null, "name": "Last day for election officials to receive absentee ballots", "type": "deadline", "election_key": "20200623", "subtype": "absentee.received_by", "date": "2020-06-30", "postmark_too_late": false}, {"state": "Oklahoma", "county": null, "name": "Last day for election officials to receive absentee ballots", "type": "deadline", "election_key": "20200630", "subtype": "absentee.received_by", "date": "2020-06-30", "postmark_too_late": true}, {"state": "Oklahoma", "county": null, "name": "Last day to vote in person", "type": "deadline", "election_key": "20200630", "subtype": "poll.in_person_by", "date": "2020-06-30"}, {"state": "Oklahoma", "county": null, "name": "Vote in person", "type": "reminder", "election_key": "20200630", "subtype": "poll.in_person_by", "date": "2020-06-30", "deadline_date": "2020-06-30", "start_date": "2020-06-30"}, {"state": "Utah", "county": null, "name": "Last day to drop off an absentee ballot", "type": "deadline", "election_key": "20200630", "subtype": "absentee.in_person_by", "date": "2020-06-30"}, {"state": "Utah", "county": null, "name": "Drop off ballot", "type": "reminder", "election_key": "20200630", "subtype": "absentee.in_person_by", "date": "2020-06-30", "deadline_date": "2020-06-30"}, {"state": "Colorado", "county": null, "name": "Mail ballot at the post office", "type": "reminder", "election_key": "20200630", "subtype": "absentee.overseas_military.received_by", "date": "2020-07-01", "postmark_too_late": true, "deadline_date": "2020-07-08", "explanation": "Ballot must be received by July 8th."}, {"state": "Delaware", "county": null, "name": "Plan to vote", "type": "reminder", "election_key": "20200707", "subtype": "poll.in_person_by", "date": "2020-07-06", "deadline_date": "2020-07-07"}, {"date": "2020-07-07", "name": "Presidential Primary", "original_date": "2020-07-07", "registration": {}, "absentee": {}, "poll": {}, "state": "Delaware", "county": null, "key": "20200707", "type": "election"}, {"date": "2020-07-07", "name": "Congressional & Presidential Primary", "original_date": "2020-07-07", "state": "New Jersey", "county": null, "key": "20200707", "type": "election"}, {"state": "Delaware", "county": null, "name": "Last day for election officials to receive absentee ballots", "type": "deadline", "election_key": "20200707", "subtype": "absentee.received_by", "date": "2020-07-07", "postmark_too_late": true}, {"state": "Delaware", "county": null, "name": "Last day to vote in person", "type": "deadline", "election_key": "20200707", "subtype": "poll.in_person_by", "date": "2020-07-07"}, {"state": "Delaware", "county": null, "name": "Vote in person", "type": "reminder", "election_key": "20200707", "subtype": "poll.in_person_by", "date": "2020-07-07", "deadline_date": "2020-07-07", "start_date": "2020-07-07"}, {"state": "Missouri", "county": null, "name": "Mail voter registration", "type": "reminder", "election_key": "20200804", "subtype": "registration.postmarked_by", "date": "2020-07-07", "postmark_too_late": false, "deadline_date": "2020-07-08", "explanation": "Voter registration must be postmarked by July 8th."}, {"state": "Colorado", "county": null, "name": "Last day for election officials to receive military and overseas ballots", "type": "deadline", "election_key": "20200630", "subtype": "absentee.overseas_military.received_by", "date": "2020-07-08", "postmark_too_late": true}, {"state": "Missouri", "county": null, "name": "Last day to register to vote in person", "type": "deadline", "election_key": "20200804", "subtype": "registration.in_person_by", "date": "2020-07-08"}, {"state": "Missouri", "county": null, "name": "Last day to postmark voter registration form", "type": "deadline", "election_key": "20200804", "subtype": "registration.postmarked_by", "date": "2020-07-08", "postmark_too_late": false}, {"state": "Missouri", "county": null, "name": "Last day to register to vote online", "type": "deadline", "election_key": "20200804", "subtype": "registration.online_by", "date": "2020-07-08"}, {"state": "Missouri", "county": null, "name": "Register to vote in person", "type": "reminder", "election_key": "20200804", "subtype": "registration.in_person_by", "date": "2020-07-08", "deadline_date": "2020-07-08"}, {"state": "Missouri", "county": null, "name": "Mail voter registration at the post office", "type": "reminder", "election_key": "20200804", "subtype": "registration.postmarked_by", "date": "2020-07-08", "postmark_too_late": false, "deadline_date": "2020-07-08", "explanation": "Voter registration must be postmarked by July 8th."}, {"state": "Missouri", "county": null, "name": "Register to vote online", "type": "reminder", "election_key": "20200804", "subtype": "registration.online_by", "date": "2020-07-08", "deadline_date": "2020-07-08"}, {"date": "2020-07-11", "name": "Presidential Primary", "original_date": "2020-07-11", "state": "Louisiana", "county": null, "key": "20200711", "type": "election"}, {"date": "2020-07-12", "name": "Presidential Primary (Democrat)", "original_date": "2020-07-12", "state": "Puerto Rico", "county": null, "key": "20200712", "type": "election"}, {"state": "Delaware", "county": null, "name": "Mail ballot", "type": "reminder", "election_key": "20200721", "subtype": "absentee.received_by", "date": "2020-07-13", "postmark_too_late": true, "deadline_date": "2020-07-21", "explanation": "Ballot must be received by July 21st."}, {"date": "2020-07-14", "name": "Congressional Primary Run-Off (if needed)", "original_date": "2020-07-14", "state": "Alabama", "county": null, "key": "20200714", "type": "election"}, {"date": "2020-07-14", "name": "Congressional Primary", "original_date": "2020-07-14", "state": "Maine", "county": null, "key": "20200714", "type": "election"}, {"date": "2020-07-14", "name": "Congressional Primary Run-Off (if needed)", "original_date": "2020-07-14", "state": "Texas", "county": null, "key": "20200714", "type": "election"}, {"state": "Delaware", "county": null, "name": "Mail ballot at the post office", "type": "reminder", "election_key": "20200721", "subtype": "absentee.received_by", "date": "2020-07-14", "postmark_too_late": true, "deadline_date": "2020-07-21", "explanation": "Ballot must be received by July 21st."}, {"state": "Missouri", "county": null, "name": "Mail absentee application", "type": "reminder", "election_key": "20200804", "subtype": "absentee.application.received_by", "date": "2020-07-14", "postmark_too_late": true, "deadline_date": "2020-07-22", "explanation": "Absentee application must be received by July 22nd."}, {"state": "Missouri", "county": null, "name": "Mail absentee application at the post office", "type": "reminder", "election_key": "20200804", "subtype": "absentee.application.received_by", "date": "2020-07-15", "postmark_too_late": true, "deadline_date": "2020-07-22", "explanation": "Absentee application must be received by July 22nd."}, {"state": "Delaware", "county": null, "name": "Plan to vote", "type": "reminder", "election_key": "20200721", "subtype": "poll.in_person_by", "date": "2020-07-20", "deadline_date": "2020-07-21"}, {"date": "2020-07-21", "name": "School Board Elections", "original_date": "2020-07-21", "sources": ["https://elections.delaware.gov/calendar/2020ElectionCalendar.pdf"], "absentee": {}, "poll": {}, "state": "Delaware", "county": null, "key": "20200721", "type": "election"}, {"state": "Delaware", "county": null, "name": "Last day for election officials to receive absentee ballots", "type": "deadline", "election_key": "20200721", "subtype": "absentee.received_by", "date": "2020-07-21", "postmark_too_late": true}, {"state": "Delaware", "county": null, "name": "Last day to vote in person", "type": "deadline", "election_key": "20200721", "subtype": "poll.in_person_by", "date": "2020-07-21"}, {"state": "Delaware", "county": null, "name": "Vote in person", "type": "reminder", "election_key": "20200721", "subtype": "poll.in_person_by", "date": "2020-07-21", "deadline_date": "2020-07-21", "start_date": "2020-07-21"}, {"state": "Missouri", "county": null, "name": "Last day for election officials to receive absentee applications", "type": "deadline", "election_key": "20200804", "subtype": "absentee.application.received_by", "date": "2020-07-22", "postmark_too_late": true}, {"state": "Missouri", "county": null, "name": "Mail ballot", "type": "reminder", "election_key": "20200804", "subtype": "absentee.received_by", "date": "2020-07-27", "postmark_too_late": true, "deadline_date": "2020-08-04", "explanation": "Ballot must be received by August 4th."}, {"state": "Missouri", "county": null, "name": "Mail ballot at the post office", "type": "reminder", "election_key": "20200804", "subtype": "absentee.received_by", "date": "2020-07-28", "postmark_too_late": true, "deadline_date": "2020-08-04", "explanation": "Ballot must be received by August 4th."}, {"date": "2020-08-01", "name": "Congressional Primary", "original_date": "2020-08-01", "state": "U.S. Virgin Islands", "county": null, "key": "20200801", "type": "election"}, {"date": "2020-08-04", "name": "Congressional Primary", "original_date": "2020-08-04", "state": "Arizona", "county": null, "key": "20200804", "type": "election"}, {"date": "2020-08-04", "name": "Congressional Primary", "original_date": "2020-08-04", "state": "Kansas", "county": null, "key": "20200804", "type": "election"}, {"date": "2020-08-04", "name": "Congressional Primary", "original_date": "2020-08-04", "state": "Michigan", "county": null, "key": "20200804", "type": "election"}, {"date": "2020-08-04", "name": "Congressional Primary", "original_date": "2020-08-04", "registration": {}, "absentee": {}, "state": "Missouri", "county": null, "key": "20200804", "type": "election"}, {"date": "2020-08-04", "name": "Congressional Primary", "original_date": "2020-08-04", "state": "Washington", "county": null, "key": "20200804", "type": "election"}, {"state": "Missouri", "county": null, "name": "Last day for election officials to receive absentee ballots", "type": "deadline", "election_key": "20200804", "subtype": "absentee.received_by", "date": "2020-08-04", "postmark_too_late": true}, {"date": "2020-08-06", "name": "Congressional Primary", "original_date": "2020-08-06", "state": "Tennessee", "county": null, "key": "20200806", "type": "election"}, {"date": "2020-08-08", "name": "Congressional Primary", "original_date": "2020-08-08", "state": "Hawaii", "county": null, "key": "20200808", "type": "election"}, {"date": "2020-08-11", "name": "Presidential Primary", "original_date": "2020-08-11", "state": "Connecticut", "county": null, "key": "20200811", "type": "election"}, {"date": "2020-08-11", "name": "Congressional Primary Run-off (if needed)", "original_date": "2020-08-11", "state": "Georgia", "county": null, "key": "20200811", "type": "election"}, {"date": "2020-08-11", "name": "Congresssional Primary", "original_date": "2020-08-11", "state": "Minnesota", "county": null, "key": "20200811", "type": "election"}, {"date": "2020-08-11", "name": "Congressional Primary Run-Off (if needed)", "original_date": "2020-08-11", "state": "South Dakota", "county": null, "key": "20200811", "type": "election"}, {"date": "2020-08-11", "name": "Congressional Primary", "original_date": "2020-08-11", "state": "Vermont", "county": null, "key": "20200811", "type": "election"}, {"date": "2020-08-11", "name": "Congressional Primary", "original_date": "2020-08-11", "state": "Wisconsin", "county": null, "key": "20200811", "type": "election"}, {"state": "Delaware", "county": null, "name": "Mail voter registration", "type": "reminder", "election_key": "20200915", "subtype": "registration.received_by", "date": "2020-08-14", "postmark_too_late": true, "deadline_date": "2020-08-22", "explanation": "Voter registration must be received by August 22nd."}, {"state": "Delaware", "county": null, "name": "Mail voter registration at the post office", "type": "reminder", "election_key": "20200915", "subtype": "registration.received_by", "date": "2020-08-15", "postmark_too_late": true, "deadline_date": "2020-08-22", "explanation": "Voter registration must be received by August 22nd."}, {"state": "Oklahoma", "county": null, "name": "Mail ballot", "type": "reminder", "election_key": "20200825", "subtype": "absentee.received_by", "date": "2020-08-17", "postmark_too_late": true, "deadline_date": "2020-08-25", "explanation": "Ballot must be received by August 25th."}, {"date": "2020-08-18", "name": "Congressional Primary", "original_date": "2020-08-18", "state": "Alaska", "county": null, "key": "20200818", "type": "election"}, {"date": "2020-08-18", "name": "Congressional Primary", "original_date": "2020-08-18", "state": "Florida", "county": null, "key": "20200818", "type": "election"}, {"date": "2020-08-18", "name": "Congressional Primary", "original_date": "2020-08-18", "state": "Wyoming", "county": null, "key": "20200818", "type": "election"}, {"state": "Oklahoma", "county": null, "name": "Mail ballot at the post office", "type": "reminder", "election_key": "20200825", "subtype": "absentee.received_by", "date": "2020-08-18", "postmark_too_late": true, "deadline_date": "2020-08-25", "explanation": "Ballot must be received by August 25th."}, {"state": "Delaware", "county": null, "name": "Last day for election officials to receive voter registration form", "type": "deadline", "election_key": "20200915", "subtype": "registration.received_by", "date": "2020-08-22", "postmark_too_late": true}, {"state": "Oklahoma", "county": null, "name": "Last day to drop off an absentee ballot", "type": "deadline", "election_key": "20200825", "subtype": "absentee.in_person_by", "date": "2020-08-22"}, {"state": "Oklahoma", "county": null, "name": "Drop off ballot", "type": "reminder", "election_key": "20200825", "subtype": "absentee.in_person_by", "date": "2020-08-22", "deadline_date": "2020-08-22"}, {"state": "Oklahoma", "county": null, "name": "Plan to vote", "type": "reminder", "election_key": "20200825", "subtype": "poll.in_person_by", "date": "2020-08-24", "deadline_date": "2020-08-25"}, {"date": "2020-08-25", "name": "Congressional Primary Run-off (if needed)", "original_date": "2020-08-25", "sources": ["https://www.ok.gov/elections/Election_Info/2020_Election_Calendar.html"], "register": {}, "absentee": {}, "poll": {}, "state": "Oklahoma", "county": null, "key": "20200825", "type": "election"}, {"state": "Oklahoma", "county": null, "name": "Last day for election officials to receive absentee ballots", "type": "deadline", "election_key": "20200825", "subtype": "absentee.received_by", "date": "2020-08-25", "postmark_too_late": true}, {"state": "Oklahoma", "county": null, "name": "Last day to vote in person", "type": "deadline", "election_key": "20200825", "subtype": "poll.in_person_by", "date": "2020-08-25"}, {"state": "Oklahoma", "county": null, "name": "Vote in person", "type": "reminder", "election_key": "20200825", "subtype": "poll.in_person_by", "date": "2020-08-25", "deadline_date": "2020-08-25", "start_date": "2020-08-25"}, {"date": "2020-08-29", "name": "Congressional Primary", "original_date": "2020-08-29", "state": "Guam", "county": null, "key": "20200829", "type": "election"}, {"date": "2020-09-01", "name": "Congressional Primary", "original_date": "2020-09-01", "state": "Massachusetts", "county": null, "key": "20200901", "type": "election"}, {"state": "Delaware", "county": null, "name": "Mail ballot", "type": "reminder", "election_key": "20200915", "subtype": "absentee.received_by", "date": "2020-09-07", "postmark_too_late": true, "deadline_date": "2020-09-15", "explanation": "Ballot must be received by September 15th."}, {"date": "2020-09-08", "name": "Congressional Primary", "original_date": "2020-09-08", "state": "New Hampshire", "county": null, "key": "20200908", "type": "election"}, {"date": "2020-09-08", "name": "Congressional Primary", "original_date": "2020-09-08", "state": "Rhode Island", "county": null, "key": "20200908", "type": "election"}, {"state": "Delaware", "county": null, "name": "Mail ballot at the post office", "type": "reminder", "election_key": "20200915", "subtype": "absentee.received_by", "date": "2020-09-08", "postmark_too_late": true, "deadline_date": "2020-09-15", "explanation": "Ballot must be received by September 15th."}, {"state": "Delaware", "county": null, "name": "Plan to vote", "type": "reminder", "election_key": "20200915", "subtype": "poll.in_person_by", "date": "2020-09-14", "deadline_date": "2020-09-15"}, {"date": "2020-09-15", "name": "Congressional Primary", "original_date": "2020-09-15", "registration": {}, "absentee": {}, "poll": {}, "state": "Delaware", "county": null, "key": "20200915", "type": "election"}, {"state": "Delaware", "county": null, "name": "Last day for election officials to receive absentee ballots", "type": "deadline", "election_key": "20200915", "subtype": "absentee.received_by", "date": "2020-09-15", "postmark_too_late": true}, {"state": "Delaware", "county": null, "name": "Last day to vote in person", "type": "deadline", "election_key": "20200915", "subtype": "poll.in_person_by", "date": "2020-09-15"}, {"state": "Delaware", "county": null, "name": "Vote in person", "type": "reminder", "election_key": "20200915", "subtype": "poll.in_person_by", "date": "2020-09-15", "deadline_date": "2020-09-15", "start_date": "2020-09-15"}, {"state": "Delaware", "county": null, "name": "Mail voter registration", "type": "reminder", "election_key": "20201103", "subtype": "registration.received_by", "date": "2020-10-02", "postmark_too_late": true, "deadline_date": "2020-10-10", "explanation": "Voter registration must be received by October 10th."}, {"state": "South Carolina", "county": null, "name": "Last day to register to vote in person", "type": "deadline", "election_key": "20201103", "subtype": "registration.in_person_by", "date": "2020-10-02"}, {"state": "South Carolina", "county": null, "name": "Register to vote in person", "type": "reminder", "election_key": "20201103", "subtype": "registration.in_person_by", "date": "2020-10-02", "deadline_date": "2020-10-02"}, {"state": "Delaware", "county": null, "name": "Mail voter registration at the post office", "type": "reminder", "election_key": "20201103", "subtype": "registration.received_by", "date": "2020-10-03", "postmark_too_late": true, "deadline_date": "2020-10-10", "explanation": "Voter registration must be received by October 10th."}, {"state": "South Carolina", "county": null, "name": "Last day to register to vote online", "type": "deadline", "election_key": "20201103", "subtype": "registration.online_by", "date": "2020-10-04"}, {"state": "South Carolina", "county": null, "name": "Register to vote online", "type": "reminder", "election_key": "20201103", "subtype": "registration.online_by", "date": "2020-10-04", "deadline_date": "2020-10-04"}, {"state": "South Carolina", "county": null, "name": "Mail voter registration", "type": "reminder", "election_key": "20201103", "subtype": "registration.postmarked_by", "date": "2020-10-04", "postmark_too_late": false, "deadline_date": "2020-10-05", "explanation": "Voter registration must be postmarked by October 5th."}, {"state": "South Carolina", "county": null, "name": "Last day to postmark voter registration form", "type": "deadline", "election_key": "20201103", "subtype": "registration.postmarked_by", "date": "2020-10-05", "postmark_too_late": false}, {"state": "South Carolina", "county": null, "name": "Mail voter registration at the post office", "type": "reminder", "election_key": "20201103", "subtype": "registration.postmarked_by", "date": "2020-10-05", "postmark_too_late": false, "deadline_date": "2020-10-05", "explanation": "Voter registration must be postmarked by October 5th."}, {"state": "Missouri", "county": null, "name": "Mail voter registration", "type": "reminder", "election_key": "20201103", "subtype": "registration.postmarked_by", "date": "2020-10-06", "postmark_too_late": false, "deadline_date": "2020-10-07", "explanation": "Voter registration must be postmarked by October 7th."}, {"state": "New York", "county": null, "name": "Mail voter registration", "type": "reminder", "election_key": "20201103", "subtype": "registration.received_by", "date": "2020-10-06", "postmark_too_late": true, "deadline_date": "2020-10-14", "explanation": "Voter registration must be received by October 14th."}, {"state": "Missouri", "county": null, "name": "Last day to register to vote in person", "type": "deadline", "election_key": "20201103", "subtype": "registration.in_person_by", "date": "2020-10-07"}, {"state": "Missouri", "county": null, "name": "Last day to postmark voter registration form", "type": "deadline", "election_key": "20201103", "subtype": "registration.postmarked_by", "date": "2020-10-07", "postmark_too_late": false}, {"state": "Missouri", "county": null, "name": "Last day to register to vote online", "type": "deadline", "election_key": "20201103", "subtype": "registration.online_by", "date": "2020-10-07"}, {"state": "Missouri", "county": null, "name": "Register to vote in person", "type": "reminder", "election_key": "20201103", "subtype": "registration.in_person_by", "date": "2020-10-07", "deadline_date": "2020-10-07"}, {"state": "Missouri", "county": null, "name": "Mail voter registration at the post office", "type": "reminder", "election_key": "20201103", "subtype": "registration.postmarked_by", "date": "2020-10-07", "postmark_too_late": false, "deadline_date": "2020-10-07", "explanation": "Voter registration must be postmarked by October 7th."}, {"state": "Missouri", "county": null, "name": "Register to vote online", "type": "reminder", "election_key": "20201103", "subtype": "registration.online_by", "date": "2020-10-07", "deadline_date": "2020-10-07"}, {"state": "New York", "county": null, "name": "Mail voter registration at the post office", "type": "reminder", "election_key": "20201103", "subtype": "registration.received_by", "date": "2020-10-07", "postmark_too_late": true, "deadline_date": "2020-10-14", "explanation": "Voter registration must be received by October 14th."}, {"state": "New York", "county": null, "name": "Last day to postmark voter registration form", "type": "deadline", "election_key": "20201103", "subtype": "registration.postmarked_by", "date": "2020-10-09", "postmark_too_late": true}, {"state": "Delaware", "county": null, "name": "Last day for election officials to receive voter registration form", "type": "deadline", "election_key": "20201103", "subtype": "registration.received_by", "date": "2020-10-10", "postmark_too_late": true}, {"state": "New York", "county": null, "name": "Last day to register to vote in person", "type": "deadline", "election_key": "20201103", "subtype": "registration.in_person_by", "date": "2020-10-10"}, {"state": "New York", "county": null, "name": "Register to vote in person", "type": "reminder", "election_key": "20201103", "subtype": "registration.in_person_by", "date": "2020-10-10", "deadline_date": "2020-10-10"}, {"state": "New York", "county": null, "name": "Last day for election officials to receive voter registration form", "type": "deadline", "election_key": "20201103", "subtype": "registration.received_by", "date": "2020-10-14", "postmark_too_late": true}, {"state": "Colorado", "county": null, "name": "Mail voter registration", "type": "reminder", "election_key": "20201103", "subtype": "registration.received_by", "date": "2020-10-18", "postmark_too_late": true, "deadline_date": "2020-10-26", "explanation": "Voter registration must be received by October 26th."}, {"state": "Colorado", "county": null, "name": "Mail voter registration at the post office", "type": "reminder", "election_key": "20201103", "subtype": "registration.received_by", "date": "2020-10-19", "postmark_too_late": true, "deadline_date": "2020-10-26", "explanation": "Voter registration must be received by October 26th."}, {"state": "North Carolina", "county": null, "name": "Mail absentee application", "type": "reminder", "election_key": "20201103", "subtype": "absentee.application.received_by", "date": "2020-10-19", "postmark_too_late": true, "deadline_date": "2020-10-27", "explanation": "Absentee application must be received by October 27th."}, {"state": "North Carolina", "county": null, "name": "Mail absentee application at the post office", "type": "reminder", "election_key": "20201103", "subtype": "absentee.application.received_by", "date": "2020-10-20", "postmark_too_late": true, "deadline_date": "2020-10-27", "explanation": "Absentee application must be received by October 27th."}, {"state": "Colorado", "county": null, "name": "Last day for election officials to receive voter registration form", "type": "deadline", "election_key": "20201103", "subtype": "registration.received_by", "date": "2020-10-26", "postmark_too_late": true}, {"state": "Delaware", "county": null, "name": "Mail ballot", "type": "reminder", "election_key": "20201103", "subtype": "absentee.received_by", "date": "2020-10-26", "postmark_too_late": true, "deadline_date": "2020-11-03", "explanation": "Ballot must be received by November 3rd."}, {"state": "New York", "county": null, "name": "Mail absentee application", "type": "reminder", "election_key": "20201103", "subtype": "absentee.application.postmarked_by", "date": "2020-10-26", "postmark_too_late": false, "deadline_date": "2020-10-27", "explanation": "Absentee application must be postmarked by October 27th."}, {"state": "Oklahoma", "county": null, "name": "Mail ballot", "type": "reminder", "election_key": "20201103", "subtype": "absentee.received_by", "date": "2020-10-26", "postmark_too_late": true, "deadline_date": "2020-11-03", "explanation": "Ballot must be received by November 3rd."}, {"state": "Delaware", "county": null, "name": "Mail ballot at the post office", "type": "reminder", "election_key": "20201103", "subtype": "absentee.received_by", "date": "2020-10-27", "postmark_too_late": true, "deadline_date": "2020-11-03", "explanation": "Ballot must be received by November 3rd."}, {"state": "New York", "county": null, "name": "Last day to postmark absentee applications", "type": "deadline", "election_key": "20201103", "subtype": "absentee.application.postmarked_by", "date": "2020-10-27", "postmark_too_late": false}, {"state": "New York", "county": null, "name": "Mail absentee application at the post office", "type": "reminder", "election_key": "20201103", "subtype": "absentee.application.postmarked_by", "date": "2020-10-27", "postmark_too_late": false, "deadline_date": "2020-10-27", "explanation": "Absentee application must be postmarked by October 27th."}, {"state": "North Carolina", "county": null, "name": "Last day to drop off an absentee ballot", "type": "deadline", "election_key": "20201103", "subtype": "absentee.in_person_by", "date": "2020-10-27"}, {"state": "North Carolina", "county": null, "name": "Last day for election officials to receive absentee applications", "type": "deadline", "election_key": "20201103", "subtype": "absentee.application.received_by", "date": "2020-10-27", "postmark_too_late": true}, {"state": "North Carolina", "county": null, "name": "Last day to hand deliver an absentee applications", "type": "deadline", "election_key": "20201103", "subtype": "absentee.application.in_person_by", "date": "2020-10-27"}, {"state": "North Carolina", "county": null, "name": "Drop off ballot", "type": "reminder", "election_key": "20201103", "subtype": "absentee.in_person_by", "date": "2020-10-27", "deadline_date": "2020-10-27"}, {"state": "North Carolina", "county": null, "name": "Drop off absentee application", "type": "reminder", "election_key": "20201103", "subtype": "absentee.application.in_person_by", "date": "2020-10-27", "deadline_date": "2020-10-27"}, {"state": "Oklahoma", "county": null, "name": "Mail ballot at the post office", "type": "reminder", "election_key": "20201103", "subtype": "absentee.received_by", "date": "2020-10-27", "postmark_too_late": true, "deadline_date": "2020-11-03", "explanation": "Ballot must be received by November 3rd."}, {"state": "North Carolina", "county": null, "name": "Mail ballot", "type": "reminder", "election_key": "20201103", "subtype": "absentee.received_by", "date": "2020-10-29", "postmark_too_late": true, "deadline_date": "2020-11-06", "explanation": "Ballot must be received by November 6th."}, {"state": "North Carolina", "county": null, "name": "Mail ballot at the post office", "type": "reminder", "election_key": "20201103", "subtype": "absentee.received_by", "date": "2020-10-30", "postmark_too_late": true, "deadline_date": "2020-11-06", "explanation": "Ballot must be received by November 6th."}, {"state": "South Carolina", "county": null, "name": "Last day to apply online for a mail-in ballot", "type": "deadline", "election_key": "20201103", "subtype": "absentee.application.online_by", "date": "2020-10-30"}, {"state": "South Carolina", "county": null, "name": "Apply for an absentee ballot online", "type": "reminder", "election_key": "20201103", "subtype": "absentee.application.online_by", "date": "2020-10-30", "deadline_date": "2020-10-30"}, {"state": "Oklahoma", "county": null, "name": "Last day to drop off an absentee ballot", "type": "deadline", "election_key": "20201103", "subtype": "absentee.in_person_by", "date": "2020-10-31"}, {"state": "Oklahoma", "county": null, "name": "Drop off ballot", "type": "reminder", "election_key": "20201103", "subtype": "absentee.in_person_by", "date": "2020-10-31", "deadline_date": "2020-10-31"}, {"state": "New York", "county": null, "name": "Mail ballot", "type": "reminder", "election_key": "20201103", "subtype": "absentee.postmarked_by", "date": "2020-11-01", "postmark_too_late": false, "deadline_date": "2020-11-02", "explanation": "Ballot must be postmarked by November 2nd."}, {"state": "Colorado", "county": null, "name": "Plan to vote", "type": "reminder", "election_key": "20201103", "subtype": "poll.in_person_by", "date": "2020-11-02", "deadline_date": "2020-11-03"}, {"state": "Delaware", "county": null, "name": "Plan to vote", "type": "reminder", "election_key": "20201103", "subtype": "poll.in_person_by", "date": "2020-11-02", "deadline_date": "2020-11-03"}, {"state": "New York", "county": null, "name": "Last day to postmark absentee ballots", "type": "deadline", "election_key": "20201103", "subtype": "absentee.postmarked_by", "date": "2020-11-02", "postmark_too_late": false}, {"state": "New York", "county": null, "name": "Last day to hand deliver an absentee applications", "type": "deadline", "election_key": "20201103", "subtype": "absentee.application.in_person_by", "date": "2020-11-02"}, {"state": "New York", "county": null, "name": "Mail ballot at the post office", "type": "reminder", "election_key": "20201103", "subtype": "absentee.postmarked_by", "date": "2020-11-02", "postmark_too_late": false, "deadline_date": "2020-11-02", "explanation": "Ballot must be postmarked by November 2nd."}, {"state": "New York", "county": null, "name": "Drop off absentee application", "type": "reminder", "election_key": "20201103", "subtype": "absentee.application.in_person_by", "date": "2020-11-02", "deadline_date": "2020-11-02"}, {"state": "Oklahoma", "county": null, "name": "Plan to vote", "type": "reminder", "election_key": "20201103", "subtype": "poll.in_person_by", "date": "2020-11-02", "deadline_date": "2020-11-03"}, {"state": "South Carolina", "county": null, "name": "Plan to vote", "type": "reminder", "election_key": "20201103", "subtype": "poll.in_person_by", "date": "2020-11-02", "deadline_date": "2020-11-03"}, {"state": "Utah", "county": null, "name": "Plan to vote", "type": "reminder", "election_key": "20201103", "subtype": "poll.in_person_by", "date": "2020-11-02", "deadline_date": "2020-11-03"}, {"date": "2020-11-03", "name": "General (Presidential) Election", "original_date": "2020-11-03", "key": "20201103", "state": null, "county": null, "type": "election"}, {"state": "Colorado", "county": null, "name": "Last day to vote in person", "type": "deadline", "election_key": "20201103", "subtype": "poll.in_person_by", "date": "2020-11-03"}, {"state": "Colorado", "county": null, "name": "Last day to register to vote in person", "type": "deadline", "election_key": "20201103", "subtype": "registration.in_person_by", "date": "2020-11-03"}, {"state": "Colorado", "county": null, "name": "Vote in person", "type": "reminder", "election_key": "20201103", "subtype": "poll.in_person_by", "date": "2020-11-03", "deadline_date": "2020-11-03", "start_date": "2020-11-03"}, {"state": "Colorado", "county": null, "name": "Register to vote in person", "type": "reminder", "election_key": "20201103", "subtype": "registration.in_person_by", "date": "2020-11-03", "deadline_date": "2020-11-03"}, {"state": "Delaware", "county": null, "name": "Last day for election officials to receive absentee ballots", "type": "deadline", "election_key": "20201103", "subtype": "absentee.received_by", "date": "2020-11-03", "postmark_too_late": true}, {"state": "Delaware", "county": null, "name": "Last day to vote in person", "type": "deadline", "election_key": "20201103", "subtype": "poll.in_person_by", "date": "2020-11-03"}, {"state": "Delaware", "county": null, "name": "Vote in person", "type": "reminder", "election_key": "20201103", "subtype": "poll.in_person_by", "date": "2020-11-03", "deadline_date": "2020-11-03", "start_date": "2020-11-03"}, {"state": "New York", "county": null, "name": "Last day to drop off an absentee ballot", "type": "deadline", "election_key": "20201103", "subtype": "absentee.in_person_by", "date": "2020-11-03"}, {"state": "New York", "county": null, "name": "Drop off ballot", "type": "reminder", "election_key": "20201103", "subtype": "absentee.in_person_by", "date": "2020-11-03", "deadline_date": "2020-11-03"}, {"state": "North Carolina", "county": null, "name": "Last day to postmark absentee ballots", "type": "deadline", "election_key": "20201103", "subtype": "absentee.postmarked_by", "date": "2020-11-03", "postmark_too_late": true}, {"state": "Oklahoma", "county": null, "name": "Last day for election officials to receive absentee ballots", "type": "deadline", "election_key": "20201103", "subtype": "absentee.received_by", "date": "2020-11-03", "postmark_too_late": true}, {"state": "Oklahoma", "county": null, "name": "Last day to vote in person", "type": "deadline", "election_key": "20201103", "subtype": "poll.in_person_by", "date": "2020-11-03"}, {"state": "Oklahoma", "county": null, "name": "Vote in person", "type": "reminder", "election_key": "20201103", "subtype": "poll.in_person_by", "date": "2020-11-03", "deadline_date": "2020-11-03", "start_date": "2020-11-03"}, {"state": "South Carolina", "county": null, "name": "Last day to vote in person", "type": "deadline", "election_key": "20201103", "subtype": "poll.in_person_by", "date": "2020-11-03"}, {"state": "South Carolina", "county": null, "name": "Vote in person", "type": "reminder", "election_key": "20201103", "subtype": "poll.in_person_by", "date": "2020-11-03", "deadline_date": "2020-11-03", "start_date": "2020-11-03"}, {"state": "Utah", "county": null, "name": "Last day to drop off an absentee ballot", "type": "deadline", "election_key": "20201103", "subtype": "absentee.in_person_by", "date": "2020-11-03"}, {"state": "Utah", "county": null, "name": "Last day to vote in person", "type": "deadline", "election_key": "20201103", "subtype": "poll.in_person_by", "date": "2020-11-03"}, {"state": "Utah", "county": null, "name": "Drop off ballot", "type": "reminder", "election_key": "20201103", "subtype": "absentee.in_person_by", "date": "2020-11-03", "deadline_date": "2020-11-03"}, {"state": "Utah", "county": null, "name": "Vote in person", "type": "reminder", "election_key": "20201103", "subtype": "poll.in_person_by", "date": "2020-11-03", "deadline_date": "2020-11-03", "start_date": "2020-11-03"}, {"state": "Colorado", "county": null, "name": "Mail ballot", "type": "reminder", "election_key": "20201103", "subtype": "absentee.overseas_military.received_by", "date": "2020-11-04", "postmark_too_late": true, "deadline_date": "2020-11-12", "explanation": "Ballot must be received by November 12th."}, {"state": "Colorado", "county": null, "name": "Mail ballot at the post office", "type": "reminder", "election_key": "20201103", "subtype": "absentee.overseas_military.received_by", "date": "2020-11-05", "postmark_too_late": true, "deadline_date": "2020-11-12", "explanation": "Ballot must be received by November 12th."}, {"state": "North Carolina", "county": null, "name": "Last day for election officials to receive absentee ballots", "type": "deadline", "election_key": "20201103", "subtype": "absentee.received_by", "date": "2020-11-06", "postmark_too_late": true}, {"state": "New York", "county": null, "name": "Last day for election officials to receive absentee ballots", "type": "deadline", "election_key": "20201103", "subtype": "absentee.received_by", "date": "2020-11-10", "postmark_too_late": false}, {"state": "Colorado", "county": null, "name": "Last day for election officials to receive military and overseas ballots", "type": "deadline", "election_key": "20201103", "subtype": "absentee.overseas_military.received_by", "date": "2020-11-12", "postmark_too_late": true}, {"date": "2020-12-05", "name": "General Run-Off (if needed)", "original_date": "2020-12-05", "state": "Louisiana", "county": null, "key": "20201205", "type": "election"}, {"date": "2021-01-05", "name": "General Run-Off (if needed)", "original_date": "2021-01-05", "state": "Georgia", "county": null, "key": "20210105", "type": "election"}], "url": "https://electioncal.us/en/", "source": "https://electioncal.us/en/all-voter.json"}